qtdatasetviewer/__init__.py
qtdatasetviewer/abstract_convert_to_pil.py
qtdatasetviewer/qt_dataset_viewer.py
qtdatasetviewer-0.0.4.dist-info/LICENSE
qtdatasetviewer-0.0.4.dist-info/METADATA
qtdatasetviewer-0.0.4.dist-info/WHEEL
qtdatasetviewer-0.0.4.dist-info/RECORD
