Metadata-Version: 2.1
Name: qtdatasetviewer
Version: 0.0.4
Summary: Torch dataset explorer
Home-page: https://github.com/toretak/qtdatasetviewer
License: MIT
Keywords: python,package,torch,dataset,poetry
Author: Toretak
Author-email: toretak@gmail.com
Maintainer: Toretak
Maintainer-email: toretak@gmail.com
Requires-Python: >=3.8
Classifier: License :: OSI Approved :: MIT License
Classifier: Programming Language :: Python :: 3
Classifier: Programming Language :: Python :: 3.8
Classifier: Programming Language :: Python :: 3.9
Classifier: Programming Language :: Python :: 3.10
Classifier: Programming Language :: Python :: 3.11
Requires-Dist: pyqt5 (>=5.15)
Requires-Dist: torch (>=1.11.1)
Project-URL: Repository, https://github.com/toretak/qtdatasetviewer
